CHANGES
COPYING
LICENSE
MANIFEST.in
NOTICE
README.md
jibebuy.py
jibebuy_test.py
setup.py
python_jibebuy.egg-info/PKG-INFO
python_jibebuy.egg-info/SOURCES.txt
python_jibebuy.egg-info/dependency_links.txt
python_jibebuy.egg-info/requires.txt
python_jibebuy.egg-info/top_level.txt