Metadata-Version: 1.1
Name: python-jibebuy
Version: 0.9.0
Summary: A python wrapper for the Jibebuy REST API
Home-page: https://github.com/pjtpj/python-jibebuy
Author: Jibebuy, Inc.
Author-email: support@jibebuy.com.
License: Apache License 2.0
Keywords: jibebuy api
Platform: UNKNOWN
Classifier: Development Status :: 4 - Beta
Classifier: Intended Audience :: Developers
Classifier: License :: OSI Approved :: Apache Software License
Classifier: Topic :: Software Development :: Libraries :: Python Modules
Classifier: Topic :: Internet
